catwire/__init__.py
catwire/apple.py
catwire/ble_pdu_adv.py
catwire/microsoft.py
catwire-0.1.0.dist-info/WHEEL
catwire-0.1.0.dist-info/METADATA
catwire-0.1.0.dist-info/RECORD
