Metadata-Version: 2.1
Name: catwire
Version: 0.1.0
Summary: 
Author: Johannes K Becker
Author-email: jkbecker@bu.edu
Requires-Python: >=3.7,<4.0
Classifier: Programming Language :: Python :: 3
Classifier: Programming Language :: Python :: 3.7
Classifier: Programming Language :: Python :: 3.8
Classifier: Programming Language :: Python :: 3.9
Requires-Dist: kaitaistruct (>=0.9,<0.10)
